[
  {
    "image_id": "campanile-de-bayeux-jpg",
    "mean_score_prediction": 4.979136089532403
  },
  {
    "image_id": "ta-img-20160102-094736-jpg",
    "mean_score_prediction": 5.330774160720466
  },
  {
    "image_id": "media-cdn-tripadvisor-com_deux-nuit-lors-d-un-seminaire-jpg",
    "mean_score_prediction": 4.8699908661074005
  },
  {
    "image_id": "salle-de-restaurant-a-jpg",
    "mean_score_prediction": 4.586975068712491
  },
  {
    "image_id": "media-cdn-tripadvisor-com_dining-room-jpg",
    "mean_score_prediction": 4.810261705733865
  },
  {
    "image_id": "outside-seating-jpg",
    "mean_score_prediction": 4.86927043846481
  },
  {
    "image_id": "media-cdn-tripadvisor-com_campanile-rouen-nord-jpg",
    "mean_score_prediction": 4.759518635662971
  },
  {
    "image_id": "media-cdn-tripadvisor-com_sehr-bequem-jpg",
    "mean_score_prediction": 4.150859046423648
  },
  {
    "image_id": "perfect-food-jpg",
    "mean_score_prediction": 3.8019281439403585
  },
  {
    "image_id": "media-cdn-tripadvisor-com_campanile-lille-euralille-jpg",
    "mean_score_prediction": 4.879022637702292
  },
  {
    "image_id": "veiw-from-breakfast-jpg",
    "mean_score_prediction": 4.676494367298005
  },
  {
    "image_id": "media-cdn-tripadvisor-com_photo4jpg-jpg",
    "mean_score_prediction": 4.145108241013077
  },
  {
    "image_id": "media-cdn-tripadvisor-com_campanile-calais-jpg",
    "mean_score_prediction": 5.478778179123765
  },
  {
    "image_id": "media-cdn-tripadvisor-com_campanile-strasbourg-jpg",
    "mean_score_prediction": 4.01205561307961
  },
  {
    "image_id": "tartine-aux-legumes-du-jpg",
    "mean_score_prediction": 4.481740388451726
  },
  {
    "image_id": "steak-kebabs-jpg",
    "mean_score_prediction": 5.259359444215079
  },
  {
    "image_id": "img-20170810-224823-716-jpg",
    "mean_score_prediction": 4.933016622744617
  },
  {
    "image_id": "buffet-breakfast-jpg",
    "mean_score_prediction": 4.672558749327436
  },
  {
    "image_id": "media-cdn-tripadvisor-com_campanile-rennes-est-jpg",
    "mean_score_prediction": 5.171895327512175
  },
  {
    "image_id": "coffee-tea-making-facilities-jpg",
    "mean_score_prediction": 3.9427348571998664
  },
  {
    "image_id": "grosse-kaseplatte-fur-jpg",
    "mean_score_prediction": 4.71955876904758
  },
  {
    "image_id": "salade-auvergnate-jpg",
    "mean_score_prediction": 4.8333827735623345
  },
  {
    "image_id": "20191209-082656-largejpg-jpg",
    "mean_score_prediction": 4.902746737730922
  },
  {
    "image_id": "20190915-122754-largejpg-jpg",
    "mean_score_prediction": 5.2785203295061365
  },
  {
    "image_id": "dessert-sous-forme-de-jpg",
    "mean_score_prediction": 4.315803927822344
  },
  {
    "image_id": "20190625-075625-largejpg-jpg",
    "mean_score_prediction": 5.082016296641086
  },
  {
    "image_id": "campanile-livry-gargan-jpg",
    "mean_score_prediction": 4.856328065681737
  },
  {
    "image_id": "kyriad-disneyland-resort-jpg",
    "mean_score_prediction": 4.132924636433017
  },
  {
    "image_id": "petit-dejeuner-jpg",
    "mean_score_prediction": 4.329498139279167
  },
  {
    "image_id": "buffet-jpg",
    "mean_score_prediction": 5.61211584735247
  },
  {
    "image_id": "breakfast-options-from-jpg",
    "mean_score_prediction": 4.637933417252498
  },
  {
    "image_id": "campanile-chartres-jpg",
    "mean_score_prediction": 4.0084090593789625
  },
  {
    "image_id": "pate-de-pizza-jpg",
    "mean_score_prediction": 5.104194518426084
  },
  {
    "image_id": "img-20191222-215609-largejpg-jpg",
    "mean_score_prediction": 5.1376776928664185
  },
  {
    "image_id": "edificio-del-buffet-restaurant-jpg",
    "mean_score_prediction": 5.095800797761967
  },
  {
    "image_id": "buffet-d-entrees-sur-jpg",
    "mean_score_prediction": 5.465310968033009
  },
  {
    "image_id": "campanile-roissy-jpg",
    "mean_score_prediction": 4.530445347758359
  },
  {
    "image_id": "colazione-jpg",
    "mean_score_prediction": 5.141805127408588
  },
  {
    "image_id": "media-cdn-tripadvisor-com_campanile-nantes-st-herblain-jpg",
    "mean_score_prediction": 4.479527722185594
  },
  {
    "image_id": "20190218-191256-largejpg-jpg",
    "mean_score_prediction": 4.832822651427705
  },
  {
    "image_id": "img-20180605-080729-largejpg-jpg",
    "mean_score_prediction": 4.8252318578306586
  },
  {
    "image_id": "20160613-080722-largejpg-jpg",
    "mean_score_prediction": 5.2273029280545416
  },
  {
    "image_id": "campanile-bordeaux-centre-jpg",
    "mean_score_prediction": 4.163481480518158
  },
  {
    "image_id": "campanile-grenoble-nord-jpg",
    "mean_score_prediction": 5.16996711678803
  },
  {
    "image_id": "speisesaal-jpg",
    "mean_score_prediction": 4.411943176361092
  },
  {
    "image_id": "salle-pour-petits-dejeuners-jpg",
    "mean_score_prediction": 5.009269276461737
  },
  {
    "image_id": "campanile-antibes-juan-jpg",
    "mean_score_prediction": 4.876371497404762
  },
  {
    "image_id": "media-cdn-tripadvisor-com_salon-du-bar-jpg",
    "mean_score_prediction": 5.210581759791239
  },
  {
    "image_id": "greasy-cooked-breakfast-jpg",
    "mean_score_prediction": 4.683042529213708
  },
  {
    "image_id": "nice-dinner-but-ot-very-jpg",
    "mean_score_prediction": 4.899092041159747
  },
  {
    "image_id": "media-cdn-tripadvisor-com_photo1jpg-jpg",
    "mean_score_prediction": 3.954508718578836
  },
  {
    "image_id": "campanile-la-ferte-bernard-jpg",
    "mean_score_prediction": 5.087450167558927
  },
  {
    "image_id": "radiateur-jpg",
    "mean_score_prediction": 4.3618190528286505
  },
  {
    "image_id": "img-20190727-192336-largejpg-jpg",
    "mean_score_prediction": 4.95675778973964
  },
  {
    "image_id": "media-cdn-tripadvisor-com_campanile-chartres-jpg",
    "mean_score_prediction": 4.334851973457262
  },
  {
    "image_id": "red-red-wine-jpg",
    "mean_score_prediction": 3.894025015140187
  },
  {
    "image_id": "media-cdn-tripadvisor-com_magny-le-hongre-jpg",
    "mean_score_prediction": 4.919228228593511
  },
  {
    "image_id": "petit-dejeuner-2-jpg",
    "mean_score_prediction": 5.28309987278044
  },
  {
    "image_id": "buffet-super-complet-jpg",
    "mean_score_prediction": 4.66702211991651
  },
  {
    "image_id": "le-diner-jpg",
    "mean_score_prediction": 5.138735809770878
  },
  {
    "image_id": "2009-08-12-nice-campanile-jpg",
    "mean_score_prediction": 4.932345725159394
  },
  {
    "image_id": "ontbijt-en-restaurantruimte-jpg",
    "mean_score_prediction": 4.57435524390894
  },
  {
    "image_id": "la-pizza-a-la-chevre-jpg",
    "mean_score_prediction": 4.983851412485819
  },
  {
    "image_id": "a-fuir-jpg",
    "mean_score_prediction": 5.390072217145644
  },
  {
    "image_id": "20190723-062334-largejpg-jpg",
    "mean_score_prediction": 5.5447092265603715
  },
  {
    "image_id": "salle-d-eau-jpg",
    "mean_score_prediction": 4.628051921361475
  },
  {
    "image_id": "coin-salle-de-bains-jpg",
    "mean_score_prediction": 4.699960761514376
  },
  {
    "image_id": "img-20170806-wa0033-largejpg-jpg",
    "mean_score_prediction": 4.510872133813336
  },
  {
    "image_id": "media-cdn-tripadvisor-com_campanile-de-bayeux-jpg",
    "mean_score_prediction": 5.1230052202008665
  },
  {
    "image_id": "campanile-valence-sud-jpg",
    "mean_score_prediction": 4.437213753343713
  },
  {
    "image_id": "20190218-143344-largejpg-jpg",
    "mean_score_prediction": 4.500985915707133
  },
  {
    "image_id": "tevens-desk-en-ontbijt-jpg",
    "mean_score_prediction": 4.766496599397669
  },
  {
    "image_id": "media-cdn-tripadvisor-com_restaurant-jpg",
    "mean_score_prediction": 4.090632002976008
  },
  {
    "image_id": "ta-img-20190217-221733-jpg",
    "mean_score_prediction": 4.965835005394183
  },
  {
    "image_id": "20161030-222527-largejpg-jpg",
    "mean_score_prediction": 5.423096859929501
  },
  {
    "image_id": "bar-jpg",
    "mean_score_prediction": 5.062510364223272
  },
  {
    "image_id": "campanile-metz-centre-jpg",
    "mean_score_prediction": 5.390382342298835
  },
  {
    "image_id": "campanile-paris-est-porte-jpg",
    "mean_score_prediction": 4.410930777536123
  },
  {
    "image_id": "buffet-de-desserts-jpg",
    "mean_score_prediction": 4.600763020585873
  },
  {
    "image_id": "this-is-a-picture-of-jpg",
    "mean_score_prediction": 5.114294512730794
  },
  {
    "image_id": "campanile-rouen-nord-jpg",
    "mean_score_prediction": 4.564891469708527
  },
  {
    "image_id": "20190830-091035-largejpg-jpg",
    "mean_score_prediction": 5.025556024847901
  },
  {
    "image_id": "buffet-des-desserts-au-jpg",
    "mean_score_prediction": 4.88228678208543
  },
  {
    "image_id": "20191005-072201-largejpg-jpg",
    "mean_score_prediction": 4.417095708777197
  },
  {
    "image_id": "ta-img-20160326-222104-jpg",
    "mean_score_prediction": 4.611362111216295
  },
  {
    "image_id": "bang-your-head-on-this-jpg",
    "mean_score_prediction": 4.367672915970616
  },
  {
    "image_id": "entrecote-jpg",
    "mean_score_prediction": 5.185357141250279
  },
  {
    "image_id": "img-20170810-193327-807-jpg",
    "mean_score_prediction": 5.02190143284497
  },
  {
    "image_id": "img-20180624-wa0002-largejpg-jpg",
    "mean_score_prediction": 4.373137759987003
  },
  {
    "image_id": "camera-jpg",
    "mean_score_prediction": 5.16193906305125
  },
  {
    "image_id": "media-cdn-tripadvisor-com_307b-jpg",
    "mean_score_prediction": 5.089206112948887
  },
  {
    "image_id": "20190625-075623-largejpg-jpg",
    "mean_score_prediction": 5.196090202691266
  },
  {
    "image_id": "campanile-saintes-jpg",
    "mean_score_prediction": 4.608298936916071
  },
  {
    "image_id": "entrada-jpg",
    "mean_score_prediction": 4.828001193098316
  },
  {
    "image_id": "central-area-and-accommodation-jpg",
    "mean_score_prediction": 4.84516399113636
  },
  {
    "image_id": "fruhstuck-jpg",
    "mean_score_prediction": 5.2325627114623785
  },
  {
    "image_id": "20190813-091316-largejpg-jpg",
    "mean_score_prediction": 4.765985159785487
  },
  {
    "image_id": "la-bouteille-d-eau-jpg",
    "mean_score_prediction": 5.069592247935361
  },
  {
    "image_id": "salle-de-restaurant-decor-jpg",
    "mean_score_prediction": 4.593385060608853
  },
  {
    "image_id": "magny-le-hongre-jpg",
    "mean_score_prediction": 4.24892533240029
  },
  {
    "image_id": "20191005-205844-largejpg-jpg",
    "mean_score_prediction": 5.121690211504756
  },
  {
    "image_id": "campanile-chalon-sur-jpg",
    "mean_score_prediction": 4.799425051860453
  },
  {
    "image_id": "media-cdn-tripadvisor-com_campanile-dijon-congres-jpg",
    "mean_score_prediction": 3.985746357885091
  },
  {
    "image_id": "clean-and-no-molds-and-jpg",
    "mean_score_prediction": 5.5177063387818635
  },
  {
    "image_id": "20190218-143428-largejpg-jpg",
    "mean_score_prediction": 4.687051763001364
  },
  {
    "image_id": "vista-desde-la-habitacion-jpg",
    "mean_score_prediction": 4.727983823635441
  },
  {
    "image_id": "breakfast-jpg",
    "mean_score_prediction": 5.325198363803793
  },
  {
    "image_id": "media-cdn-tripadvisor-com_campanile-beauvais-jpg",
    "mean_score_prediction": 4.520194142285618
  },
  {
    "image_id": "20161030-222523-largejpg-jpg",
    "mean_score_prediction": 4.408389847412764
  },
  {
    "image_id": "img-20190512-221434-largejpg-jpg",
    "mean_score_prediction": 5.0880879345713765
  },
  {
    "image_id": "davanzale-finestra-e-jpg",
    "mean_score_prediction": 4.36103008686041
  },
  {
    "image_id": "restaurant-au-petit-gari-jpg",
    "mean_score_prediction": 4.672416365621302
  },
  {
    "image_id": "buffet-le-matin-jpg",
    "mean_score_prediction": 5.159796165378793
  },
  {
    "image_id": "307b-jpg",
    "mean_score_prediction": 4.866317790467292
  },
  {
    "image_id": "restaurant-open-every-jpg",
    "mean_score_prediction": 4.855994655517861
  },
  {
    "image_id": "20181117-005738-largejpg-jpg",
    "mean_score_prediction": 4.6231785487616435
  },
  {
    "image_id": "campanile-aix-en-provence-jpg",
    "mean_score_prediction": 4.424824611778604
  },
  {
    "image_id": "20170401-232552-largejpg_rotated_90-jpg",
    "mean_score_prediction": 4.633346810849616
  },
  {
    "image_id": "le-bar-jpg",
    "mean_score_prediction": 3.607598322914896
  },
  {
    "image_id": "campanile-nantes-centre-jpg",
    "mean_score_prediction": 5.211636867257766
  },
  {
    "image_id": "img-20191017-074011-largejpg-jpg",
    "mean_score_prediction": 4.534692137065576
  },
  {
    "image_id": "pickpocket-signs-displayed-jpg",
    "mean_score_prediction": 4.734518835088238
  },
  {
    "image_id": "media-cdn-tripadvisor-com_photo9jpg-jpg",
    "mean_score_prediction": 4.446632958075497
  },
  {
    "image_id": "img-20181109-175128-933-jpg",
    "mean_score_prediction": 4.9302232970512705
  },
  {
    "image_id": "le-salon-d-accueil-jpg",
    "mean_score_prediction": 5.312824398453813
  },
  {
    "image_id": "colazione-e-buffet-di-jpg",
    "mean_score_prediction": 5.399118762870785
  },
  {
    "image_id": "ta-img-20190226-213100-jpg",
    "mean_score_prediction": 4.150425238094158
  },
  {
    "image_id": "campanile-carcassonne-jpg",
    "mean_score_prediction": 4.993504233731073
  },
  {
    "image_id": "20170715-122501-largejpg-jpg",
    "mean_score_prediction": 4.370685216461425
  },
  {
    "image_id": "greasy-bacon-jpg",
    "mean_score_prediction": 4.404344069760555
  },
  {
    "image_id": "campanile-dunkerque-armbouts-jpg",
    "mean_score_prediction": 4.665461889844664
  },
  {
    "image_id": "20190218-170549-largejpg-jpg",
    "mean_score_prediction": 5.247598960719188
  },
  {
    "image_id": "food-jpg",
    "mean_score_prediction": 5.4817371011085925
  },
  {
    "image_id": "media-cdn-tripadvisor-com_petit-dejeuner-jpg",
    "mean_score_prediction": 4.838797582255211
  },
  {
    "image_id": "campanile-val-de-france-jpg",
    "mean_score_prediction": 5.062305457602633
  },
  {
    "image_id": "exterieur-pantalon-de-jpg",
    "mean_score_prediction": 3.7662990424969394
  },
  {
    "image_id": "the-flat-screen-jpg",
    "mean_score_prediction": 4.598140774600324
  },
  {
    "image_id": "img-20180605-081128-largejpg-jpg",
    "mean_score_prediction": 4.820912916006819
  },
  {
    "image_id": "terrasse-du-restaurant-jpg",
    "mean_score_prediction": 5.309245520540571
  },
  {
    "image_id": "le-restaurant-jpg",
    "mean_score_prediction": 4.455155489835306
  },
  {
    "image_id": "desserts-jpg",
    "mean_score_prediction": 5.190980387327727
  },
  {
    "image_id": "campanile-nimes-sud-caissargue-jpg",
    "mean_score_prediction": 4.747726329049328
  },
  {
    "image_id": "het-restaurant-met-de-jpg",
    "mean_score_prediction": 5.3647117484106275
  },
  {
    "image_id": "20160102-091511-largejpg-jpg",
    "mean_score_prediction": 4.9991677114558115
  },
  {
    "image_id": "img-20180605-081206-largejpg-jpg",
    "mean_score_prediction": 4.152007172626327
  },
  {
    "image_id": "ontbijt-jpg",
    "mean_score_prediction": 6.071413288187614
  },
  {
    "image_id": "20170715-122512-largejpg-jpg",
    "mean_score_prediction": 5.250354224757757
  },
  {
    "image_id": "ta-img-20160909-124104-jpg",
    "mean_score_prediction": 5.305333024745778
  },
  {
    "image_id": "20170807-164134-largejpg-jpg",
    "mean_score_prediction": 4.922413357093319
  },
  {
    "image_id": "sala-colazione-jpg",
    "mean_score_prediction": 3.919084726182973
  },
  {
    "image_id": "20181117-005744-largejpg-jpg",
    "mean_score_prediction": 4.278275651173317
  },
  {
    "image_id": "buffet-des-desserts-jpg",
    "mean_score_prediction": 4.334595127751527
  },
  {
    "image_id": "desde-la-ventana-jpg",
    "mean_score_prediction": 4.109176349867312
  },
  {
    "image_id": "campanile-amiens-centre-jpg",
    "mean_score_prediction": 4.197287844889615
  },
  {
    "image_id": "la-planche-mixte-charcuterie-jpg",
    "mean_score_prediction": 5.044295525469352
  },
  {
    "image_id": "presentation-du-petit-jpg",
    "mean_score_prediction": 5.368594914882124
  },
  {
    "image_id": "salle-du-restaurant-jpg",
    "mean_score_prediction": 4.445672203062713
  },
  {
    "image_id": "having-breakfast-jpg",
    "mean_score_prediction": 4.999842422315851
  },
  {
    "image_id": "le-lit-jpg",
    "mean_score_prediction": 5.210546677582897
  },
  {
    "image_id": "media-cdn-tripadvisor-com_hotel-campanile-creteil-jpg",
    "mean_score_prediction": 5.0829764772206545
  },
  {
    "image_id": "hotel-restaurant-jpg",
    "mean_score_prediction": 5.245899231813382
  },
  {
    "image_id": "restaurant-avec-buffets-jpg",
    "mean_score_prediction": 5.4319409294346315
  },
  {
    "image_id": "img-20180605-080553-largejpg-jpg",
    "mean_score_prediction": 4.967780440751085
  },
  {
    "image_id": "ta-img-20160326-222046-jpg",
    "mean_score_prediction": 4.790294639766216
  },
  {
    "image_id": "img-20180605-080753-largejpg-jpg",
    "mean_score_prediction": 4.645880301912257
  },
  {
    "image_id": "lobby-avec-grand-ecran-jpg",
    "mean_score_prediction": 5.334249719238869
  },
  {
    "image_id": "media-cdn-tripadvisor-com_habitacion-jpg",
    "mean_score_prediction": 4.5502838114480255
  },
  {
    "image_id": "le-buffet-jpg",
    "mean_score_prediction": 4.58594131434802
  },
  {
    "image_id": "une-formule-fort-souple-jpg",
    "mean_score_prediction": 3.4906788179917925
  },
  {
    "image_id": "campanile-cahors-jpg",
    "mean_score_prediction": 5.261751026439015
  },
  {
    "image_id": "20160516-091520-largejpg-jpg",
    "mean_score_prediction": 4.750922815549529
  },
  {
    "image_id": "20181117-005727-largejpg-jpg",
    "mean_score_prediction": 4.861749843461439
  },
  {
    "image_id": "walking-upto-the-breakfast-jpg",
    "mean_score_prediction": 4.583129652396565
  },
  {
    "image_id": "media-cdn-tripadvisor-com_campanile-issoudun-jpg",
    "mean_score_prediction": 5.1669834837357485
  },
  {
    "image_id": "buffet-de-dessert-jpg",
    "mean_score_prediction": 4.6592665275675245
  },
  {
    "image_id": "le-buffet-a-9-80-jpg",
    "mean_score_prediction": 5.262304214469623
  },
  {
    "image_id": "20170731-094943-largejpg-jpg",
    "mean_score_prediction": 4.827001692701742
  },
  {
    "image_id": "pain-decongele-et-mal-jpg",
    "mean_score_prediction": 4.986411413279711
  },
  {
    "image_id": "zalig-op-terras-genieten-jpg",
    "mean_score_prediction": 4.244819399094922
  },
  {
    "image_id": "salon-jpg",
    "mean_score_prediction": 4.820932883711066
  },
  {
    "image_id": "20191005-072116-largejpg-jpg",
    "mean_score_prediction": 4.9181333000015
  },
  {
    "image_id": "pizzeria-feu-de-bois-jpg",
    "mean_score_prediction": 5.071645112126134
  },
  {
    "image_id": "campanile-saint-malo-jpg",
    "mean_score_prediction": 4.444688095649326
  },
  {
    "image_id": "campanile-chantilly-jpg",
    "mean_score_prediction": 3.3839466199377775
  },
  {
    "image_id": "20191210-083706-largejpg-jpg",
    "mean_score_prediction": 4.800406138325343
  },
  {
    "image_id": "20170731-094855-largejpg-jpg",
    "mean_score_prediction": 4.876338474918157
  },
  {
    "image_id": "sejour-campanile-colmar-jpg",
    "mean_score_prediction": 4.520907952042762
  },
  {
    "image_id": "baignoire-sabot-jpg",
    "mean_score_prediction": 4.798395963036455
  },
  {
    "image_id": "campanile-toulouse-ouest-jpg",
    "mean_score_prediction": 5.032473633677
  },
  {
    "image_id": "media-cdn-tripadvisor-com_campanile-lyon-centre-jpg",
    "mean_score_prediction": 4.579745753057068
  },
  {
    "image_id": "filename-p6080066-jpg-jpg",
    "mean_score_prediction": 4.719709739496466
  },
  {
    "image_id": "campanile-villejust-za-jpg",
    "mean_score_prediction": 5.808461681613153
  },
  {
    "image_id": "img-20190514-210845-largejpg-jpg",
    "mean_score_prediction": 5.115522083477117
  },
  {
    "image_id": "20190830-090331-largejpg-jpg",
    "mean_score_prediction": 4.88363812858006
  },
  {
    "image_id": "versailles-petit-trion-jpg",
    "mean_score_prediction": 5.212883343370777
  },
  {
    "image_id": "entree-accueil-et-restaurant-jpg",
    "mean_score_prediction": 3.9959716845032744
  },
  {
    "image_id": "habitacion-jpg",
    "mean_score_prediction": 4.296442038690657
  },
  {
    "image_id": "buffet-des-dessert-jpg",
    "mean_score_prediction": 5.1846610018692445
  },
  {
    "image_id": "campanile-paris-15-tour-jpg",
    "mean_score_prediction": 4.807582182780607
  },
  {
    "image_id": "een-deel-van-het-ontbijt-jpg",
    "mean_score_prediction": 5.05571076227352
  },
  {
    "image_id": "20191209-082650-largejpg-jpg",
    "mean_score_prediction": 4.917388345929794
  },
  {
    "image_id": "parque-de-estacionamento-jpg",
    "mean_score_prediction": 4.527820432927001
  },
  {
    "image_id": "media-cdn-tripadvisor-com_this-is-campnile-tour-jpg",
    "mean_score_prediction": 5.070802662929054
  },
  {
    "image_id": "queue-de-tomates-trouvee-jpg",
    "mean_score_prediction": 5.082239766255952
  },
  {
    "image_id": "delicieux-cafe-gourmand-jpg",
    "mean_score_prediction": 5.312628226227389
  },
  {
    "image_id": "20190218-143411-largejpg-jpg",
    "mean_score_prediction": 5.122148325521266
  },
  {
    "image_id": "media-cdn-tripadvisor-com_campanile-roissy-jpg",
    "mean_score_prediction": 4.867798819730524
  },
  {
    "image_id": "media-cdn-tripadvisor-com_campanile-paris-xv-tour-jpg",
    "mean_score_prediction": 5.191383339100867
  },
  {
    "image_id": "campanile-paris-19-la-jpg",
    "mean_score_prediction": 5.130859136639629
  },
  {
    "image_id": "caption-jpg",
    "mean_score_prediction": 4.894092277616437
  },
  {
    "image_id": "img-20180605-085426-largejpg-jpg",
    "mean_score_prediction": 4.337521916542755
  },
  {
    "image_id": "tarif-de-la-chambre-remarquez-jpg",
    "mean_score_prediction": 4.225342832447495
  },
  {
    "image_id": "campanile-issoudun-jpg",
    "mean_score_prediction": 5.003227241362765
  },
  {
    "image_id": "media-cdn-tripadvisor-com_buffet-de-dessert-jpg",
    "mean_score_prediction": 5.034692244313192
  },
  {
    "image_id": "20170401-230758-largejpg-jpg",
    "mean_score_prediction": 4.59834125796624
  },
  {
    "image_id": "self-service-canteen-jpg",
    "mean_score_prediction": 4.902259223883448
  },
  {
    "image_id": "coin-bureau-jpg",
    "mean_score_prediction": 4.309875944338273
  },
  {
    "image_id": "croissants-restant-a-jpg",
    "mean_score_prediction": 5.312087841652101
  },
  {
    "image_id": "quiche-jpg",
    "mean_score_prediction": 4.42079868367
  },
  {
    "image_id": "small-elevator-jpg",
    "mean_score_prediction": 4.130753843270213
  },
  {
    "image_id": "20160715-191022-largejpg-jpg",
    "mean_score_prediction": 4.440529635607163
  },
  {
    "image_id": "campanile-villepinte-jpg",
    "mean_score_prediction": 5.70972324137756
  },
  {
    "image_id": "le-grand-buffet-de-dessert-jpg",
    "mean_score_prediction": 4.787528378830757
  },
  {
    "image_id": "detente-jpg",
    "mean_score_prediction": 5.072430126805557
  },
  {
    "image_id": "media-cdn-tripadvisor-com_2009-08-12-nice-campanile-jpg",
    "mean_score_prediction": 4.7589886362839025
  },
  {
    "image_id": "media-cdn-tripadvisor-com_campanile-amiens-centre-jpg",
    "mean_score_prediction": 5.022744439091184
  },
  {
    "image_id": "media-cdn-tripadvisor-com_le-buffet-du-petit-dejeuner-jpg",
    "mean_score_prediction": 4.4101036578576895
  },
  {
    "image_id": "20160518-193409-largejpg-jpg",
    "mean_score_prediction": 5.0292976084165275
  },
  {
    "image_id": "ground-floor-room-jpg",
    "mean_score_prediction": 5.186912819852296
  },
  {
    "image_id": "tables-non-debarrassees-jpg",
    "mean_score_prediction": 5.290499183211068
  },
  {
    "image_id": "le-buffet-du-petit-dejeuner-jpg",
    "mean_score_prediction": 4.570839261636138
  },
  {
    "image_id": "20181117-005751-largejpg-jpg",
    "mean_score_prediction": 4.733981846133247
  },
  {
    "image_id": "filename-p1000253-jpg-jpg",
    "mean_score_prediction": 5.029784002137603
  },
  {
    "image_id": "media-cdn-tripadvisor-com_campanile-laon-jpg",
    "mean_score_prediction": 4.595747891566134
  },
  {
    "image_id": "campanile-poitiers-site-jpg",
    "mean_score_prediction": 5.785207530677326
  },
  {
    "image_id": "20160101-183819-largejpg-jpg",
    "mean_score_prediction": 4.401174963684753
  },
  {
    "image_id": "campanile-nantes-st-herblain-jpg",
    "mean_score_prediction": 4.8880606952589005
  },
  {
    "image_id": "media-cdn-tripadvisor-com_photo0jpg-jpg",
    "mean_score_prediction": 4.778259627753869
  },
  {
    "image_id": "pancakes-for-breakfast-jpg",
    "mean_score_prediction": 5.792865919742326
  },
  {
    "image_id": "campanile-laval-nord-jpg",
    "mean_score_prediction": 5.506243912064747
  },
  {
    "image_id": "buffet-suite-jpg",
    "mean_score_prediction": 3.284196215643176
  },
  {
    "image_id": "filename-img-3654-jpg-jpg",
    "mean_score_prediction": 4.033293158639935
  },
  {
    "image_id": "u-campanile-jpg",
    "mean_score_prediction": 4.603093159923446
  },
  {
    "image_id": "photo0jpg-jpg",
    "mean_score_prediction": 5.132681020462769
  },
  {
    "image_id": "dinner-jpg",
    "mean_score_prediction": 5.436789035971742
  },
  {
    "image_id": "filename-p1000257-jpg-jpg",
    "mean_score_prediction": 3.9866345655607347
  },
  {
    "image_id": "ontbijtbuffet-jpg",
    "mean_score_prediction": 4.667945357301505
  },
  {
    "image_id": "french-cooked-breakfast-jpg",
    "mean_score_prediction": 5.564715353626525
  },
  {
    "image_id": "allow-time-for-local-jpg",
    "mean_score_prediction": 4.376663215503868
  },
  {
    "image_id": "campanile-lille-sud-chr-jpg",
    "mean_score_prediction": 5.166540623176843
  },
  {
    "image_id": "le-buffet-des-desserts-jpg",
    "mean_score_prediction": 5.344161008742958
  },
  {
    "image_id": "campanile-evry-ouest-jpg",
    "mean_score_prediction": 4.323774864940788
  },
  {
    "image_id": "original-jpg",
    "mean_score_prediction": 4.557737998664379
  },
  {
    "image_id": "campanile-lille-nord-jpg",
    "mean_score_prediction": 5.1878377777466085
  },
  {
    "image_id": "dsc-0117-largejpg-jpg",
    "mean_score_prediction": 4.433673615312728
  },
  {
    "image_id": "carte-du-restaurant-jpg",
    "mean_score_prediction": 4.308301573006247
  },
  {
    "image_id": "campanile-fontainebleau-jpg",
    "mean_score_prediction": 5.568252138562457
  },
  {
    "image_id": "media-cdn-tripadvisor-com_caption-jpg",
    "mean_score_prediction": 4.349327082178206
  },
  {
    "image_id": "20190218-143354-largejpg-jpg",
    "mean_score_prediction": 5.2345502957032295
  },
  {
    "image_id": "hall-jpg",
    "mean_score_prediction": 4.404390745294222
  },
  {
    "image_id": "tortellinis-a-la-meridionale-jpg",
    "mean_score_prediction": 4.759911906789057
  },
  {
    "image_id": "salle-de-restaurant-accueillan-jpg",
    "mean_score_prediction": 4.561140706107835
  },
  {
    "image_id": "dsc-0382-largejpg-jpg",
    "mean_score_prediction": 4.3585033940544236
  },
  {
    "image_id": "ta-img-20170319-182420-jpg",
    "mean_score_prediction": 4.642934317060281
  },
  {
    "image_id": "vue-du-restaurant-jpg",
    "mean_score_prediction": 4.60475570516428
  },
  {
    "image_id": "campanile-reims-centre-jpg",
    "mean_score_prediction": 5.342414284445113
  },
  {
    "image_id": "campanile-lille-euralille-jpg",
    "mean_score_prediction": 5.530929688778997
  },
  {
    "image_id": "aussenansicht-jpg",
    "mean_score_prediction": 4.469436204653448
  },
  {
    "image_id": "20170803-190307-largejpg_rotated_90-jpg",
    "mean_score_prediction": 4.345235289176344
  },
  {
    "image_id": "campanile-melun-sud-dammarie-jpg",
    "mean_score_prediction": 5.039775418001227
  },
  {
    "image_id": "restaurant-menu-jpg",
    "mean_score_prediction": 4.571697102848702
  },
  {
    "image_id": "campanile-meaux-jpg",
    "mean_score_prediction": 4.409585639943543
  },
  {
    "image_id": "20170513-011158-largejpg-jpg",
    "mean_score_prediction": 5.452757226281392
  },
  {
    "image_id": "campanile-paris-ouest-jpg",
    "mean_score_prediction": 4.9178812904210645
  },
  {
    "image_id": "7-jpg",
    "mean_score_prediction": 4.917654908611439
  },
  {
    "image_id": "espace-petit-dejeuner-jpg",
    "mean_score_prediction": 5.392641758980972
  },
  {
    "image_id": "media-cdn-tripadvisor-com_superbe-renovation-des-jpg",
    "mean_score_prediction": 4.687051763001364
  },
  {
    "image_id": "towards-restaurant-jpg",
    "mean_score_prediction": 4.533053599703635
  },
  {
    "image_id": "wc-jpg",
    "mean_score_prediction": 4.137399800557432
  },
  {
    "image_id": "campanile-lyon-sud-oullins-jpg",
    "mean_score_prediction": 4.603266124482616
  },
  {
    "image_id": "img-20190727-191838-largejpg-jpg",
    "mean_score_prediction": 4.970939837308833
  },
  {
    "image_id": "20171116-110521-largejpg-jpg",
    "mean_score_prediction": 4.5795503207991715
  },
  {
    "image_id": "le-buffet-petit-dejeuner-jpg",
    "mean_score_prediction": 4.72804065181117
  },
  {
    "image_id": "egg-custard-and-canele-jpg",
    "mean_score_prediction": 5.500288279130473
  },
  {
    "image_id": "la-sdb-jpg",
    "mean_score_prediction": 4.975214000907727
  },
  {
    "image_id": "collation-avec-bureau-jpg",
    "mean_score_prediction": 4.345220854840591
  },
  {
    "image_id": "campanile-rochefort-sur-jpg",
    "mean_score_prediction": 4.897900093055796
  },
  {
    "image_id": "pain-mal-cuit-jpg",
    "mean_score_prediction": 5.399614382076834
  },
  {
    "image_id": "campanile-dunkerque-est-jpg",
    "mean_score_prediction": 4.733118583644682
  },
  {
    "image_id": "20160101-183813-largejpg-jpg",
    "mean_score_prediction": 5.116563410847448
  },
  {
    "image_id": "media-cdn-tripadvisor-com_campanile-sete-balaruc-jpg",
    "mean_score_prediction": 4.483808138174936
  },
  {
    "image_id": "under-cooked-pastry-jpg",
    "mean_score_prediction": 4.425159271318989
  },
  {
    "image_id": "media-cdn-tripadvisor-com_campanile-dijon-est-saint-jpg",
    "mean_score_prediction": 4.871280456078239
  },
  {
    "image_id": "tavolino-con-caraffa-jpg",
    "mean_score_prediction": 4.388240923253761
  },
  {
    "image_id": "ta-img-20191229-071732-jpg",
    "mean_score_prediction": 4.647219885664526
  },
  {
    "image_id": "buffet-du-petit-dejeune-jpg",
    "mean_score_prediction": 3.9787866070450946
  },
  {
    "image_id": "dinner-buffet-jpg",
    "mean_score_prediction": 4.826788054371718
  },
  {
    "image_id": "media-cdn-tripadvisor-com_detente-jpg",
    "mean_score_prediction": 4.620753769188013
  },
  {
    "image_id": "img-20180605-085401-largejpg-jpg",
    "mean_score_prediction": 4.27847009870311
  },
  {
    "image_id": "media-cdn-tripadvisor-com_photo3jpg-jpg",
    "mean_score_prediction": 4.679467088659294
  },
  {
    "image_id": "filename-p1080234-jpg-jpg",
    "mean_score_prediction": 4.160138955133334
  },
  {
    "image_id": "hotel-jpg",
    "mean_score_prediction": 4.904713881222051
  },
  {
    "image_id": "campanile-nice-aeroport-jpg",
    "mean_score_prediction": 5.430842047288934
  },
  {
    "image_id": "dining-area-jpg",
    "mean_score_prediction": 5.387716142964564
  },
  {
    "image_id": "img-20180605-085950-largejpg-jpg",
    "mean_score_prediction": 4.450456756145286
  },
  {
    "image_id": "buffet-de-desserts-sur-jpg",
    "mean_score_prediction": 5.276756573817693
  },
  {
    "image_id": "media-cdn-tripadvisor-com_campanile-evry-ouest-jpg",
    "mean_score_prediction": 4.327875985829451
  },
  {
    "image_id": "view-from-dining-jpg",
    "mean_score_prediction": 4.668628380753944
  },
  {
    "image_id": "photo1jpg-jpg",
    "mean_score_prediction": 5.244472443140694
  },
  {
    "image_id": "20190523-214316-largejpg-jpg",
    "mean_score_prediction": 5.230339880217798
  },
  {
    "image_id": "andouillette-grillee-jpg",
    "mean_score_prediction": 5.097649869159795
  },
  {
    "image_id": "buffet-libre-desayuno-jpg",
    "mean_score_prediction": 4.496123409815482
  },
  {
    "image_id": "ta-img-20170319-182444-jpg",
    "mean_score_prediction": 4.215114791946689
  },
  {
    "image_id": "mojito-jpg",
    "mean_score_prediction": 4.892713623848977
  },
  {
    "image_id": "la-chambre-jpg",
    "mean_score_prediction": 5.643871046086133
  },
  {
    "image_id": "media-cdn-tripadvisor-com_buffet-petit-dejeuner-jpg",
    "mean_score_prediction": 4.689107200989383
  },
  {
    "image_id": "cote-tele-jpg",
    "mean_score_prediction": 4.20670144311589
  },
  {
    "image_id": "muestra-de-comida-del-jpg",
    "mean_score_prediction": 4.128582325893149
  },
  {
    "image_id": "20190218-143401-largejpg-jpg",
    "mean_score_prediction": 4.484783992338635
  },
  {
    "image_id": "main-dining-area-jpg",
    "mean_score_prediction": 5.313365108289872
  },
  {
    "image_id": "no-food-rotation-jpg",
    "mean_score_prediction": 4.352325397336244
  },
  {
    "image_id": "petit-dejeuner-buffet-jpg",
    "mean_score_prediction": 4.90170452860184
  },
  {
    "image_id": "salle-de-restaurant-jpg",
    "mean_score_prediction": 4.738205117493635
  },
  {
    "image_id": "media-cdn-tripadvisor-com_campanile-bordeaux-centre-jpg",
    "mean_score_prediction": 4.1848431117578
  },
  {
    "image_id": "cassolette-de-la-mer-jpg",
    "mean_score_prediction": 4.63821199911763
  },
  {
    "image_id": "media-cdn-tripadvisor-com_campanile-bollene-jpg",
    "mean_score_prediction": 5.0985561748966575
  },
  {
    "image_id": "photo4jpg-jpg",
    "mean_score_prediction": 5.515519807311648
  },
  {
    "image_id": "le-comptoir-restaurant-jpg",
    "mean_score_prediction": 4.872155206059688
  },
  {
    "image_id": "burger-du-jour-jpg",
    "mean_score_prediction": 4.587576146921492
  },
  {
    "image_id": "hotel-kyriad-paris-disneyland-jpg",
    "mean_score_prediction": 5.316238894200069
  },
  {
    "image_id": "dinne-buffet-jpg",
    "mean_score_prediction": 4.6227653964888304
  },
  {
    "image_id": "20170803-190326-largejpg_rotated_90-jpg",
    "mean_score_prediction": 4.697229421697557
  },
  {
    "image_id": "photo9jpg-jpg",
    "mean_score_prediction": 5.259788845142793
  },
  {
    "image_id": "pour-faire-du-cafe-ou-jpg",
    "mean_score_prediction": 3.863810824533175
  },
  {
    "image_id": "20170731-094926-largejpg-jpg",
    "mean_score_prediction": 5.065552401123568
  },
  {
    "image_id": "photo8jpg-jpg",
    "mean_score_prediction": 5.084738289244342
  },
  {
    "image_id": "hotel-entrance-to-reception-jpg",
    "mean_score_prediction": 4.739599965028901
  },
  {
    "image_id": "faux-filet-saignant-ou-jpg",
    "mean_score_prediction": 5.119444827316329
  },
  {
    "image_id": "buffet-entrees-jpg",
    "mean_score_prediction": 4.389152599711451
  },
  {
    "image_id": "campanile-sedan-jpg",
    "mean_score_prediction": 5.244187643984333
  },
  {
    "image_id": "dining-room-at-breakfast-jpg",
    "mean_score_prediction": 4.108424121925054
  },
  {
    "image_id": "possibilite-de-faire-jpg",
    "mean_score_prediction": 3.994392042376603
  },
  {
    "image_id": "campanile-tours-sud-chambray-jpg",
    "mean_score_prediction": 4.602972994471202
  },
  {
    "image_id": "campanile-le-mans-jpg",
    "mean_score_prediction": 4.828458827476425
  },
  {
    "image_id": "zoom-sur-les-crepes-proposee-jpg",
    "mean_score_prediction": 4.874844415055122
  },
  {
    "image_id": "bufet-jpg",
    "mean_score_prediction": 4.855030361744866
  },
  {
    "image_id": "media-cdn-tripadvisor-com_campanile-poitiers-site-jpg",
    "mean_score_prediction": 4.953600856621051
  },
  {
    "image_id": "media-cdn-tripadvisor-com_campanile-carcassonne-jpg",
    "mean_score_prediction": 3.9956331617413525
  },
  {
    "image_id": "la-colazione-jpg",
    "mean_score_prediction": 5.238892625842709
  },
  {
    "image_id": "media-cdn-tripadvisor-com_buffet-breakfast-jpg",
    "mean_score_prediction": 4.411313852891908
  },
  {
    "image_id": "photo3jpg-jpg",
    "mean_score_prediction": 4.647327190978103
  },
  {
    "image_id": "le-bufet-des-entrees-jpg",
    "mean_score_prediction": 5.185188603732968
  },
  {
    "image_id": "media-cdn-tripadvisor-com_close-to-the-town-center-jpg",
    "mean_score_prediction": 4.389172933428199
  },
  {
    "image_id": "ogni-mattina-jpg",
    "mean_score_prediction": 3.7142570035185543
  },
  {
    "image_id": "outside-restaurant-jpg",
    "mean_score_prediction": 4.672272027564759
  },
  {
    "image_id": "campanile-epone-jpg",
    "mean_score_prediction": 4.834947729308624
  },
  {
    "image_id": "campanile-reims-ouest-jpg",
    "mean_score_prediction": 5.093869449774502
  },
  {
    "image_id": "20191006-093028-largejpg-jpg",
    "mean_score_prediction": 5.290864273920306
  },
  {
    "image_id": "campanile-lens-jpg",
    "mean_score_prediction": 5.30585439008064
  },
  {
    "image_id": "buffet-d-entrees-jpg",
    "mean_score_prediction": 4.3545814686222
  },
  {
    "image_id": "media-cdn-tripadvisor-com_campanile-toulouse-ouest-jpg",
    "mean_score_prediction": 5.4854165663491585
  },
  {
    "image_id": "20170713-094249-largejpg-jpg",
    "mean_score_prediction": 4.693149145181451
  },
  {
    "image_id": "la-sala-ristorante-dehor-jpg",
    "mean_score_prediction": 4.9391575612535235
  },
  {
    "image_id": "media-cdn-tripadvisor-com_campanile-cahors-jpg",
    "mean_score_prediction": 4.690603672854195
  },
  {
    "image_id": "campanile-bollene-jpg",
    "mean_score_prediction": 4.932477178474073
  },
  {
    "image_id": "ingang-restaurant-en-jpg",
    "mean_score_prediction": 4.8904047945543425
  },
  {
    "image_id": "sanitaire-jpg",
    "mean_score_prediction": 4.474267591995158
  },
  {
    "image_id": "photo7jpg-jpg",
    "mean_score_prediction": 5.5428219396619625
  },
  {
    "image_id": "media-cdn-tripadvisor-com_hotel-kyriad-paris-disneyland-jpg",
    "mean_score_prediction": 4.51939913709748
  },
  {
    "image_id": "filename-p1000254-jpg-jpg",
    "mean_score_prediction": 4.7341370699869
  },
  {
    "image_id": "group-dinner-best-group-jpg",
    "mean_score_prediction": 4.798609850535286
  },
  {
    "image_id": "photo5jpg-jpg",
    "mean_score_prediction": 5.6507876294617745
  },
  {
    "image_id": "the-area-around-the-breakfast-jpg",
    "mean_score_prediction": 4.800406718393788
  },
  {
    "image_id": "hotel-campanile-creteil-jpg",
    "mean_score_prediction": 5.548371269174822
  },
  {
    "image_id": "le-coin-salon-jpg",
    "mean_score_prediction": 4.2775918864444975
  },
  {
    "image_id": "burger-jpg",
    "mean_score_prediction": 4.65958500637862
  },
  {
    "image_id": "hum-jpg",
    "mean_score_prediction": 4.902024048438761
  },
  {
    "image_id": "buffet-du-matin-photo-jpg",
    "mean_score_prediction": 5.708784789923811
  },
  {
    "image_id": "campanile-saint-etienne-jpg",
    "mean_score_prediction": 4.532529860880459
  },
  {
    "image_id": "campanile-saint-avold-jpg",
    "mean_score_prediction": 4.66205418930258
  },
  {
    "image_id": "toilettes-jpg",
    "mean_score_prediction": 5.041658492991701
  },
  {
    "image_id": "media-cdn-tripadvisor-com_campanile-evreux-jpg",
    "mean_score_prediction": 4.219942187486595
  },
  {
    "image_id": "campanile-dijon-est-saint-jpg",
    "mean_score_prediction": 4.887840513169067
  },
  {
    "image_id": "media-cdn-tripadvisor-com_kyriad-disneyland-resort-jpg",
    "mean_score_prediction": 4.117566571103907
  },
  {
    "image_id": "media-cdn-tripadvisor-com_hotel-kyriad-disneyland-jpg",
    "mean_score_prediction": 4.693503589936881
  },
  {
    "image_id": "hotel-kyriad-disneyland-jpg",
    "mean_score_prediction": 4.393230318076348
  },
  {
    "image_id": "campanile-annemasse-centre-jpg",
    "mean_score_prediction": 4.837837253769976
  },
  {
    "image_id": "media-cdn-tripadvisor-com_a-fuir-jpg",
    "mean_score_prediction": 4.969070566019127
  },
  {
    "image_id": "20170401-231612-largejpg-jpg",
    "mean_score_prediction": 3.995619773576891
  },
  {
    "image_id": "what-i-presumed-to-be-jpg",
    "mean_score_prediction": 4.98594843056344
  },
  {
    "image_id": "hotel-campanile-val-de-jpg",
    "mean_score_prediction": 5.347368951373937
  },
  {
    "image_id": "petit-dejeune-complet-jpg",
    "mean_score_prediction": 4.69956561717845
  },
  {
    "image_id": "il-ristorante-jpg",
    "mean_score_prediction": 3.957839401793535
  },
  {
    "image_id": "media-cdn-tripadvisor-com_hotel-jpg",
    "mean_score_prediction": 5.089204980148338
  },
  {
    "image_id": "media-cdn-tripadvisor-com_carcassonne-citta-fortificata-jpg",
    "mean_score_prediction": 4.718873269575852
  },
  {
    "image_id": "petit-dejeuner-un-batiment-jpg",
    "mean_score_prediction": 4.644652984651657
  },
  {
    "image_id": "media-cdn-tripadvisor-com_campanile-nice-aeroport-jpg",
    "mean_score_prediction": 4.855145697663829
  },
  {
    "image_id": "equipement-jpg",
    "mean_score_prediction": 3.8871716101061793
  },
  {
    "image_id": "campanile-bussy-saint-jpg",
    "mean_score_prediction": 4.717069447238828
  },
  {
    "image_id": "salle-restaurant-jpg",
    "mean_score_prediction": 4.095633755672679
  },
  {
    "image_id": "restaurant-jpg",
    "mean_score_prediction": 4.468062382857397
  },
  {
    "image_id": "media-cdn-tripadvisor-com_campanile-grenoble-nord-jpg",
    "mean_score_prediction": 5.100589418889285
  },
  {
    "image_id": "campanile-paris-xv-tour-jpg",
    "mean_score_prediction": 4.817122399981599
  },
  {
    "image_id": "deux-nuit-lors-d-un-seminaire-jpg",
    "mean_score_prediction": 4.61796902698552
  },
  {
    "image_id": "media-cdn-tripadvisor-com_campanile-torcy-jpg",
    "mean_score_prediction": 4.407502043497516
  },
  {
    "image_id": "media-cdn-tripadvisor-com_campanile-bayonne-jpg",
    "mean_score_prediction": 4.829180733766407
  },
  {
    "image_id": "escalope-a-la-provencale-jpg",
    "mean_score_prediction": 4.973831621027784
  },
  {
    "image_id": "media-cdn-tripadvisor-com_u-campanile-jpg",
    "mean_score_prediction": 5.324047770147445
  },
  {
    "image_id": "breakfast-buffet-jpg",
    "mean_score_prediction": 4.524619505544251
  },
  {
    "image_id": "20160101-183841-largejpg-jpg",
    "mean_score_prediction": 4.94210481562186
  },
  {
    "image_id": "desk-jpg",
    "mean_score_prediction": 4.493606109157554
  },
  {
    "image_id": "media-cdn-tripadvisor-com_le-buffet-jpg",
    "mean_score_prediction": 4.05597718912577
  },
  {
    "image_id": "media-cdn-tripadvisor-com_campanile-saint-malo-jpg",
    "mean_score_prediction": 5.33856857939827
  },
  {
    "image_id": "20180226-073754-largejpg-jpg",
    "mean_score_prediction": 5.383024171305806
  },
  {
    "image_id": "petit-dejeuner-3-jpg",
    "mean_score_prediction": 5.39189895655727
  },
  {
    "image_id": "reception-and-restaurant-jpg",
    "mean_score_prediction": 4.478946044306213
  },
  {
    "image_id": "buffet-dinner-jpg",
    "mean_score_prediction": 5.5139743587296834
  },
  {
    "image_id": "buffet-chaud-au-restaurant-jpg",
    "mean_score_prediction": 4.549386598984711
  },
  {
    "image_id": "breakfast-in-progress-jpg",
    "mean_score_prediction": 4.689932162960758
  },
  {
    "image_id": "media-cdn-tripadvisor-com_campanile-saint-etienne-jpg",
    "mean_score_prediction": 4.961387680959888
  },
  {
    "image_id": "20191005-215005-largejpg-jpg",
    "mean_score_prediction": 4.611920220879256
  },
  {
    "image_id": "media-cdn-tripadvisor-com_tevens-desk-en-ontbijt-jpg",
    "mean_score_prediction": 4.505767187075435
  },
  {
    "image_id": "20170809-011314-largejpg-jpg",
    "mean_score_prediction": 4.543350293482945
  },
  {
    "image_id": "media-cdn-tripadvisor-com_campanile-sedan-jpg",
    "mean_score_prediction": 4.617567097477149
  },
  {
    "image_id": "campanile-laon-jpg",
    "mean_score_prediction": 4.8001781168277375
  },
  {
    "image_id": "our-windows-from-the-jpg",
    "mean_score_prediction": 4.207952810788811
  },
  {
    "image_id": "coffee-and-light-breakfast-jpg",
    "mean_score_prediction": 5.038105603889562
  },
  {
    "image_id": "campanile-nogent-sur-jpg",
    "mean_score_prediction": 5.028998215981119
  },
  {
    "image_id": "media-cdn-tripadvisor-com_hotel-campanile-marne-jpg",
    "mean_score_prediction": 4.371984513200005
  },
  {
    "image_id": "buffet-du-petit-dejeuner-jpg",
    "mean_score_prediction": 5.629865870643698
  },
  {
    "image_id": "campanile-marseille-ouest-jpg",
    "mean_score_prediction": 4.79085317638237
  },
  {
    "image_id": "terrasse-jpg",
    "mean_score_prediction": 4.908477551776741
  },
  {
    "image_id": "what-they-called-sauce-jpg",
    "mean_score_prediction": 5.007818105674232
  },
  {
    "image_id": "bano_rotated_90-jpg",
    "mean_score_prediction": 4.471397175308084
  },
  {
    "image_id": "distanza-dalla-torre-jpg",
    "mean_score_prediction": 3.7076089717190257
  },
  {
    "image_id": "20170731-094950-largejpg-jpg",
    "mean_score_prediction": 4.55753656654997
  },
  {
    "image_id": "entree-restaurant-jpg",
    "mean_score_prediction": 4.302420755683897
  },
  {
    "image_id": "20170513-094851-largejpg-jpg",
    "mean_score_prediction": 5.216690577566624
  },
  {
    "image_id": "tarifs-petits-dejeuners-jpg",
    "mean_score_prediction": 4.417292552185245
  },
  {
    "image_id": "media-cdn-tripadvisor-com_buffet-campanille-jpg",
    "mean_score_prediction": 5.016110403412313
  },
  {
    "image_id": "media-cdn-tripadvisor-com_campanile-villepinte-jpg",
    "mean_score_prediction": 5.789127284337155
  },
  {
    "image_id": "vous-etes-plutot-tarte-jpg",
    "mean_score_prediction": 5.220181731419871
  },
  {
    "image_id": "idem-jpg",
    "mean_score_prediction": 5.250179596281669
  },
  {
    "image_id": "salle-a-manger-jpg",
    "mean_score_prediction": 4.730760503782221
  },
  {
    "image_id": "photo2jpg-jpg",
    "mean_score_prediction": 4.84294216230046
  },
  {
    "image_id": "this-is-campnile-tour-jpg",
    "mean_score_prediction": 4.643897615809692
  },
  {
    "image_id": "20170731-094934-largejpg-jpg",
    "mean_score_prediction": 5.088069997436833
  },
  {
    "image_id": "the-breakfast-buffet-jpg",
    "mean_score_prediction": 4.918366782774683
  },
  {
    "image_id": "dsc-0469-largejpg-jpg",
    "mean_score_prediction": 4.583418790643918
  },
  {
    "image_id": "campanile-dijon-congres-jpg",
    "mean_score_prediction": 5.213777652475983
  },
  {
    "image_id": "campanile-strasbourg-jpg",
    "mean_score_prediction": 4.304042473646405
  },
  {
    "image_id": "and-this-one-jpg",
    "mean_score_prediction": 4.531530709915387
  },
  {
    "image_id": "le-fameux-buffet-d-entree-jpg",
    "mean_score_prediction": 4.953262589871883
  },
  {
    "image_id": "campanile-lyon-sud-chasse-jpg",
    "mean_score_prediction": 4.915438444702886
  },
  {
    "image_id": "exterior-del-comedor-jpg",
    "mean_score_prediction": 4.706521160075681
  },
  {
    "image_id": "ta-img-20190916-083929-jpg",
    "mean_score_prediction": 4.534679956617765
  },
  {
    "image_id": "filename-campanile-hotel-jpg",
    "mean_score_prediction": 4.466774811866344
  },
  {
    "image_id": "photo6jpg-jpg",
    "mean_score_prediction": 5.4705912723293295
  },
  {
    "image_id": "img-20190925-074231-largejpg-jpg",
    "mean_score_prediction": 4.616883873630286
  },
  {
    "image_id": "petit-dejeuner-en-chambre-jpg",
    "mean_score_prediction": 4.892162710602861
  },
  {
    "image_id": "salle-de-restauration-jpg",
    "mean_score_prediction": 4.867013195049367
  },
  {
    "image_id": "media-cdn-tripadvisor-com_photo5jpg-jpg",
    "mean_score_prediction": 4.361496214829458
  },
  {
    "image_id": "campanile-chelles-jpg",
    "mean_score_prediction": 4.706659341827617
  },
  {
    "image_id": "dining-room-jpg",
    "mean_score_prediction": 4.862742038123542
  },
  {
    "image_id": "media-cdn-tripadvisor-com_photo7jpg-jpg",
    "mean_score_prediction": 3.9839877581603105
  },
  {
    "image_id": "campanile-nancy-luneville-jpg",
    "mean_score_prediction": 5.332746127009159
  },
  {
    "image_id": "campanile-nantes-ouest-jpg",
    "mean_score_prediction": 4.776750586461276
  },
  {
    "image_id": "media-cdn-tripadvisor-com_photo2jpg-jpg",
    "mean_score_prediction": 4.221696585742393
  },
  {
    "image_id": "media-cdn-tripadvisor-com_ontbijt-jpg",
    "mean_score_prediction": 5.122407389586442
  },
  {
    "image_id": "media-cdn-tripadvisor-com_buffet-dinner-jpg",
    "mean_score_prediction": 4.9224968099733815
  },
  {
    "image_id": "media-cdn-tripadvisor-com_campanile-paris-15-tour-jpg",
    "mean_score_prediction": 4.887570215534652
  },
  {
    "image_id": "la-securite-au-campanille-jpg",
    "mean_score_prediction": 4.844540029182099
  },
  {
    "image_id": "img-20170806-wa0015-largejpg-jpg",
    "mean_score_prediction": 5.402298673469886
  },
  {
    "image_id": "spacious-right-jpg",
    "mean_score_prediction": 4.447617171914317
  },
  {
    "image_id": "img-20190514-213446-largejpg-jpg",
    "mean_score_prediction": 5.0794208201696165
  },
  {
    "image_id": "20190830-090326-largejpg-jpg",
    "mean_score_prediction": 4.403650874213781
  },
  {
    "image_id": "media-cdn-tripadvisor-com_breakfast-buffet-jpg",
    "mean_score_prediction": 4.808555034498568
  },
  {
    "image_id": "buffet-campanille-jpg",
    "mean_score_prediction": 5.378029835442248
  },
  {
    "image_id": "media-cdn-tripadvisor-com_campanile-aix-en-provence-jpg",
    "mean_score_prediction": 4.383109071437502
  },
  {
    "image_id": "20181117-005731-largejpg-jpg",
    "mean_score_prediction": 4.929037074034568
  },
  {
    "image_id": "restaurant-campanile-jpg",
    "mean_score_prediction": 5.228644107177388
  },
  {
    "image_id": "20161029-100504-largejpg-jpg",
    "mean_score_prediction": 4.369965908161248
  },
  {
    "image_id": "campanile-bordeaux-ouest-jpg",
    "mean_score_prediction": 5.014641894376837
  },
  {
    "image_id": "campanile-evreux-jpg",
    "mean_score_prediction": 4.535604770098871
  },
  {
    "image_id": "20191209-083737-largejpg-jpg",
    "mean_score_prediction": 4.860099316487322
  },
  {
    "image_id": "media-cdn-tripadvisor-com_campanile-nantes-sud-jpg",
    "mean_score_prediction": 4.542463069170481
  },
  {
    "image_id": "buffet-petit-dejeuner-jpg",
    "mean_score_prediction": 4.750860201711475
  },
  {
    "image_id": "buffet-salade-jpg",
    "mean_score_prediction": 3.9910713160033993
  },
  {
    "image_id": "media-cdn-tripadvisor-com_buffet-jpg",
    "mean_score_prediction": 5.653038894657584
  },
  {
    "image_id": "media-cdn-tripadvisor-com_restaurant-avec-buffets-jpg",
    "mean_score_prediction": 5.053230320481816
  },
  {
    "image_id": "20190723-062337-largejpg-jpg",
    "mean_score_prediction": 5.371161229762947
  },
  {
    "image_id": "part-of-the-corridor-jpg",
    "mean_score_prediction": 5.156961426524504
  },
  {
    "image_id": "20191005-215945-largejpg-jpg",
    "mean_score_prediction": 4.829128323937766
  },
  {
    "image_id": "campanile-clermont-ferrand-jpg",
    "mean_score_prediction": 4.962709345891199
  },
  {
    "image_id": "le-buffet-d-entree-jpg",
    "mean_score_prediction": 4.616559108850197
  },
  {
    "image_id": "filename-img-3657-jpg-jpg",
    "mean_score_prediction": 4.038041985750169
  },
  {
    "image_id": "campanile-nantes-sud-jpg",
    "mean_score_prediction": 5.125414498259488
  },
  {
    "image_id": "20171115-165656-largejpg-jpg",
    "mean_score_prediction": 4.634418242669199
  },
  {
    "image_id": "20170608-114701-largejpg-jpg",
    "mean_score_prediction": 5.092165612965346
  },
  {
    "image_id": "buffet-beau-mais-limite-jpg",
    "mean_score_prediction": 4.345853301465468
  },
  {
    "image_id": "media-cdn-tripadvisor-com_vue-du-restaurant-jpg",
    "mean_score_prediction": 4.62310200704087
  },
  {
    "image_id": "media-cdn-tripadvisor-com_buffet-libre-desayuno-jpg",
    "mean_score_prediction": 5.3965251242916565
  },
  {
    "image_id": "sauce-tartare-dont-la-jpg",
    "mean_score_prediction": 4.582235427646083
  },
  {
    "image_id": "img-20200106-204327-largejpg-jpg",
    "mean_score_prediction": 5.12205367180286
  },
  {
    "image_id": "campanile-beauvais-jpg",
    "mean_score_prediction": 4.827081884694053
  },
  {
    "image_id": "lovely-buffet-jpg",
    "mean_score_prediction": 4.662279025185853
  },
  {
    "image_id": "stunning-jpg",
    "mean_score_prediction": 4.5151932328080875
  },
  {
    "image_id": "media-cdn-tripadvisor-com_campanile-saint-avold-jpg",
    "mean_score_prediction": 4.954480901476927
  },
  {
    "image_id": "media-cdn-tripadvisor-com_la-sdb-jpg",
    "mean_score_prediction": 4.749517183197895
  },
  {
    "image_id": "salon-du-bar-jpg",
    "mean_score_prediction": 6.111053023086924
  },
  {
    "image_id": "dsc-0122-largejpg-jpg",
    "mean_score_prediction": 4.8439257280269885
  },
  {
    "image_id": "comida-do-restaurante-jpg",
    "mean_score_prediction": 5.098234141099965
  },
  {
    "image_id": "outside-jpg",
    "mean_score_prediction": 4.8004993333961465
  },
  {
    "image_id": "campanile-colmar-aeroport-jpg",
    "mean_score_prediction": 3.819663428756982
  },
  {
    "image_id": "media-cdn-tripadvisor-com_la-chambre-jpg",
    "mean_score_prediction": 5.243006598495413
  },
  {
    "image_id": "img-20161011-wa0002-largejpg-jpg",
    "mean_score_prediction": 5.074749698236701
  },
  {
    "image_id": "un-delice-jpg",
    "mean_score_prediction": 5.308872317178611
  },
  {
    "image_id": "20180120-211150-largejpg-jpg",
    "mean_score_prediction": 5.59956959460942
  },
  {
    "image_id": "salons-jpg",
    "mean_score_prediction": 5.457319677429041
  },
  {
    "image_id": "aperitif-jpg",
    "mean_score_prediction": 4.612917036400177
  },
  {
    "image_id": "campanile-auxerre-moneteau-jpg",
    "mean_score_prediction": 4.189609471883841
  },
  {
    "image_id": "media-cdn-tripadvisor-com_photo6jpg-jpg",
    "mean_score_prediction": 4.431658375571715
  },
  {
    "image_id": "campanile-rennes-est-jpg",
    "mean_score_prediction": 5.0139229042688385
  },
  {
    "image_id": "restaurant-dans-jardin-jpg",
    "mean_score_prediction": 5.5592025390342314
  },
  {
    "image_id": "campanile-douai-cuincy-jpg",
    "mean_score_prediction": 4.24835973899178
  },
  {
    "image_id": "media-cdn-tripadvisor-com_campanile-pontarlier-jpg",
    "mean_score_prediction": 5.26423547280865
  },
  {
    "image_id": "buffet-breakfast-each-jpg",
    "mean_score_prediction": 5.151794650068041
  },
  {
    "image_id": "close-to-the-town-center-jpg",
    "mean_score_prediction": 5.019674437411595
  },
  {
    "image_id": "l-espace-buffet-dans-jpg",
    "mean_score_prediction": 4.603480216988828
  },
  {
    "image_id": "boutique-jpg",
    "mean_score_prediction": 4.743531357526081
  },
  {
    "image_id": "campanile-marseille-saint-jpg",
    "mean_score_prediction": 4.780898967583198
  },
  {
    "image_id": "interesting-color-scheme-jpg",
    "mean_score_prediction": 3.6587914571488227
  },
  {
    "image_id": "sehr-bequem-jpg",
    "mean_score_prediction": 5.037264109121679
  },
  {
    "image_id": "carcassonne-citta-fortificata-jpg",
    "mean_score_prediction": 4.558938973972545
  },
  {
    "image_id": "la-salle-du-restaurant-jpg",
    "mean_score_prediction": 4.952652546577156
  },
  {
    "image_id": "20190601-203921-largejpg-jpg",
    "mean_score_prediction": 5.703818293814038
  },
  {
    "image_id": "kyriad-a-disneyland-paris-jpg",
    "mean_score_prediction": 4.862253708305616
  },
  {
    "image_id": "img-20200118-082046-largejpg-jpg",
    "mean_score_prediction": 5.3261594975192565
  },
  {
    "image_id": "trop-bon-jpg",
    "mean_score_prediction": 5.078066977926937
  },
  {
    "image_id": "img-20191222-214921-largejpg-jpg",
    "mean_score_prediction": 4.912722698121797
  },
  {
    "image_id": "campanile-torcy-jpg",
    "mean_score_prediction": 4.803089910856215
  },
  {
    "image_id": "une-petite-entree-buffet-jpg",
    "mean_score_prediction": 5.138636773044709
  },
  {
    "image_id": "hotel-campanile-marne-jpg",
    "mean_score_prediction": 4.821415979648009
  },
  {
    "image_id": "campanile-cholet-jpg",
    "mean_score_prediction": 5.429103214817587
  },
  {
    "image_id": "media-cdn-tripadvisor-com_campanile-val-de-france-jpg",
    "mean_score_prediction": 4.812462714588037
  },
  {
    "image_id": "filename-jps-7672-jpg-jpg",
    "mean_score_prediction": 5.390780946346695
  },
  {
    "image_id": "media-cdn-tripadvisor-com_group-dinner-best-group-jpg",
    "mean_score_prediction": 5.2113372886087745
  },
  {
    "image_id": "une-pause-gouter-profitez-jpg",
    "mean_score_prediction": 5.548335083070924
  },
  {
    "image_id": "breakfast-area-jpg",
    "mean_score_prediction": 5.060372564294084
  },
  {
    "image_id": "campanile-orleans-sud-jpg",
    "mean_score_prediction": 4.892878200531413
  },
  {
    "image_id": "media-cdn-tripadvisor-com_dinner-jpg",
    "mean_score_prediction": 5.520858444524492
  },
  {
    "image_id": "dining-room-sun-room-jpg",
    "mean_score_prediction": 4.78638031625087
  },
  {
    "image_id": "campanile-sete-balaruc-jpg",
    "mean_score_prediction": 4.163246705173151
  },
  {
    "image_id": "media-cdn-tripadvisor-com_campanile-paris-ouest-jpg",
    "mean_score_prediction": 5.323532132373657
  },
  {
    "image_id": "campanile-lyon-centre-jpg",
    "mean_score_prediction": 5.060993867402431
  },
  {
    "image_id": "campanile-bayonne-jpg",
    "mean_score_prediction": 4.759910466033034
  },
  {
    "image_id": "img-20180605-080823-largejpg-jpg",
    "mean_score_prediction": 5.247875309180017
  },
  {
    "image_id": "img-20170823-210110746-jpg",
    "mean_score_prediction": 4.4523082592422725
  },
  {
    "image_id": "media-cdn-tripadvisor-com_breakfast-area-jpg",
    "mean_score_prediction": 4.898850566474721
  },
  {
    "image_id": "20170922-222600-largejpg_rotated_90-jpg",
    "mean_score_prediction": 5.101975367262639
  },
  {
    "image_id": "restaurant-breakfast-jpg",
    "mean_score_prediction": 4.40742610047073
  },
  {
    "image_id": "cafe-da-manha-jpg",
    "mean_score_prediction": 4.915383635117905
  },
  {
    "image_id": "chicken-caesar-salad-jpg",
    "mean_score_prediction": 4.750861534790602
  },
  {
    "image_id": "media-cdn-tripadvisor-com_photo8jpg-jpg",
    "mean_score_prediction": 4.506222736512427
  },
  {
    "image_id": "salon-tres-cosy-jpg",
    "mean_score_prediction": 5.454759228734474
  },
  {
    "image_id": "media-cdn-tripadvisor-com_campanile-paris-19-la-jpg",
    "mean_score_prediction": 5.456521706691262
  },
  {
    "image_id": "campanile-pontarlier-jpg",
    "mean_score_prediction": 5.374229467277473
  },
  {
    "image_id": "chambre-jpg",
    "mean_score_prediction": 4.699004939844599
  },
  {
    "image_id": "media-cdn-tripadvisor-com_hotel-restaurant-jpg",
    "mean_score_prediction": 4.605796843126882
  },
  {
    "image_id": "delicious-jpg",
    "mean_score_prediction": 5.421662063570693
  },
  {
    "image_id": "shelves-jpg",
    "mean_score_prediction": 4.352715992841695
  },
  {
    "image_id": "superbe-renovation-des-jpg",
    "mean_score_prediction": 5.150852606428089
  },
  {
    "image_id": "add-a-caption-jpg",
    "mean_score_prediction": 5.223728398604067
  },
  {
    "image_id": "campanile-calais-jpg",
    "mean_score_prediction": 5.14324254821986
  },
  {
    "image_id": "hotel-gril-campanile-jpg",
    "mean_score_prediction": 4.584819745985442
  },
  {
    "image_id": "20160612-113833-largejpg-jpg",
    "mean_score_prediction": 5.089466651382054
  },
  {
    "image_id": "20171115-165705-largejpg-jpg",
    "mean_score_prediction": 3.7224288837808217
  },
  {
    "image_id": "img-20190512-214009-largejpg-jpg",
    "mean_score_prediction": 5.219832246919395
  },
  {
    "image_id": "20190830-091021-largejpg-jpg",
    "mean_score_prediction": 5.303024830386676
  },
  {
    "image_id": "dolci-a-buffet-per-la-jpg",
    "mean_score_prediction": 5.092309397994541
  },
  {
    "image_id": "media-cdn-tripadvisor-com_kyriad-a-disneyland-paris-jpg",
    "mean_score_prediction": 4.594442213936418
  },
  {
    "image_id": "media-cdn-tripadvisor-com_campanile-reims-ouest-jpg",
    "mean_score_prediction": 4.184480869966137
  },
  {
    "image_id": "20191005-072137-largejpg-jpg",
    "mean_score_prediction": 5.0136002603394445
  },
  {
    "image_id": "terrasse-du-restaurent-jpg",
    "mean_score_prediction": 4.993674508888034
  },
  {
    "image_id": "le-lounge-jpg",
    "mean_score_prediction": 4.731133414548822
  },
  {
    "image_id": "img-20191220-200538-largejpg-jpg",
    "mean_score_prediction": 5.741812110093861
  },
  {
    "image_id": "a-welcome-cold-bottle-jpg",
    "mean_score_prediction": 5.484730697680789
  }
]